sheraf/__init__.py
sheraf/attributes/__init__.py
sheraf/attributes/blobs.py
sheraf/attributes/collections.py
sheraf/attributes/counter.py
sheraf/attributes/enum.py
sheraf/attributes/files.py
sheraf/attributes/index.py
sheraf/attributes/models.py
sheraf/attributes/password.py
sheraf/attributes/simples.py
sheraf/cli.py
sheraf/conftest.py
sheraf/constants.py
sheraf/databases.py
sheraf/exceptions.py
sheraf/health/__init__.py
sheraf/health/checks.py
sheraf/health/fixes.py
sheraf/health/utils.py
sheraf/models/__init__.py
sheraf/models/attributes.py
sheraf/models/base.py
sheraf/models/indexation.py
sheraf/models/indexmanager.py
sheraf/models/inline.py
sheraf/queryset.py
sheraf/tools/__init__.py
sheraf/tools/dicttools.py
sheraf/tools/more_itertools.py
sheraf/transactions.py
sheraf/types/__init__.py
sheraf/types/counter.py
sheraf/types/largedict.py
sheraf/types/largelist.py
sheraf/version.py
sheraf-0.5.38.dist-info/LICENSE.md
sheraf-0.5.38.dist-info/METADATA
sheraf-0.5.38.dist-info/WHEEL
sheraf-0.5.38.dist-info/entry_points.txt
sheraf-0.5.38.dist-info/RECORD
