Metadata-Version: 2.1
Name: sheraf
Version: 0.5.38
Summary: Versatile ZODB abstraction layer
Home-page: https://sheraf.readthedocs.io/en/latest/
License: MIT
Keywords: zodb,orm
Author: Yaal team
Author-email: contact@yaal.coop
Maintainer: Éloi Rivard
Maintainer-email: eloi@yaal.coop
Requires-Python: >=3.7,<4
Classifier: Framework :: ZODB
Classifier: Intended Audience :: Developers
Classifier: License :: OSI Approved :: MIT License
Classifier: Programming Language :: Python :: 3
Classifier: Programming Language :: Python :: 3.7
Classifier: Programming Language :: Python :: 3.8
Classifier: Programming Language :: Python :: 3.9
Classifier: Programming Language :: Python :: 3.10
Classifier: Programming Language :: Python :: 3.11
Classifier: Programming Language :: Python :: Implementation :: CPython
Classifier: Topic :: Software Development :: Libraries :: Python Modules
Provides-Extra: all
Provides-Extra: doc
Provides-Extra: relstorage-pg
Provides-Extra: zeo
Requires-Dist: click (>=7)
Requires-Dist: legacycrypt (>=0.3,<0.4)
Requires-Dist: psycopg2 ; extra == "all" or extra == "relstorage-pg"
Requires-Dist: psycopg2cffi ; extra == "all" or extra == "relstorage-pg"
Requires-Dist: recommonmark ; extra == "doc"
Requires-Dist: relstorage ; extra == "all" or extra == "relstorage-pg"
Requires-Dist: rich (>=10)
Requires-Dist: sphinx ; extra == "doc"
Requires-Dist: sphinx-issues ; extra == "doc"
Requires-Dist: sphinx-rtd-theme ; extra == "doc"
Requires-Dist: zeo ; extra == "all" or extra == "zeo"
Requires-Dist: zodb (>=5)
Requires-Dist: zodburi
Project-URL: Documentation, https://sheraf.readthedocs.io/en/latest/
Project-URL: Repository, https://gitlab.com/yaal/sheraf
